nolanm_portfolio_package/__init__.py
nolanm_portfolio_package/setup.py
nolanm_portfolio_package-1.0.dist-info/METADATA
nolanm_portfolio_package-1.0.dist-info/WHEEL
nolanm_portfolio_package-1.0.dist-info/entry_points.txt
nolanm_portfolio_package-1.0.dist-info/top_level.txt
nolanm_portfolio_package-1.0.dist-info/RECORD
