Metadata-Version: 2.1
Name: nolanm-portfolio-package
Version: 1.0
Summary: UNKNOWN
Home-page: UNKNOWN
License: UNKNOWN
Platform: UNKNOWN
Requires-Dist: absl-py==2.1.0
Requires-Dist: aiohttp==3.9.5
Requires-Dist: aiosignal==1.3.1
Requires-Dist: alpha-vantage==2.3.1
Requires-Dist: altair==5.3.0
Requires-Dist: anyio==4.4.0
Requires-Dist: argon2-cffi==23.1.0
Requires-Dist: argon2-cffi-bindings==21.2.0
Requires-Dist: arrow==1.3.0
Requires-Dist: asttokens==2.4.1
Requires-Dist: astunparse==1.6.3
Requires-Dist: async-lru==2.0.4
Requires-Dist: async-timeout==4.0.3
Requires-Dist: attrs==23.2.0
Requires-Dist: Babel==2.15.0
Requires-Dist: beautifulsoup4==4.12.3
Requires-Dist: bleach==6.1.0
Requires-Dist: blinker==1.8.2
Requires-Dist: cachetools==5.3.3
Requires-Dist: cassandra-driver==3.29.1
Requires-Dist: certifi==2024.2.2
Requires-Dist: cffi==1.16.0
Requires-Dist: charset-normalizer==3.3.2
Requires-Dist: click==8.1.7
Requires-Dist: colorama==0.4.6
Requires-Dist: comm==0.2.2
Requires-Dist: contourpy==1.2.1
Requires-Dist: cycler==0.12.1
Requires-Dist: DateTime==5.5
Requires-Dist: debugpy==1.8.2
Requires-Dist: decorator==5.1.1
Requires-Dist: defusedxml==0.7.1
Requires-Dist: exceptiongroup==1.2.1
Requires-Dist: executing==2.0.1
Requires-Dist: fastjsonschema==2.20.0
Requires-Dist: feedparser==6.0.11
Requires-Dist: flatbuffers==24.3.25
Requires-Dist: fonttools==4.52.4
Requires-Dist: fqdn==1.5.1
Requires-Dist: frozendict==2.4.4
Requires-Dist: frozenlist==1.4.1
Requires-Dist: gast==0.4.0
Requires-Dist: geomet==0.2.1.post1
Requires-Dist: gitdb==4.0.11
Requires-Dist: GitPython==3.1.43
Requires-Dist: google-api-core==2.19.0
Requires-Dist: google-api-python-client==2.131.0
Requires-Dist: google-auth==2.29.0
Requires-Dist: google-auth-httplib2==0.2.0
Requires-Dist: google-auth-oauthlib==1.0.0
Requires-Dist: google-pasta==0.2.0
Requires-Dist: googleapis-common-protos==1.63.0
Requires-Dist: grpcio==1.64.0
Requires-Dist: h11==0.14.0
Requires-Dist: h5py==3.11.0
Requires-Dist: html5lib==1.1
Requires-Dist: httpcore==1.0.5
Requires-Dist: httplib2==0.22.0
Requires-Dist: httpx==0.27.0
Requires-Dist: idna==3.7
Requires-Dist: importlib-metadata==7.1.0
Requires-Dist: importlib-resources==6.4.0
Requires-Dist: iniconfig==2.0.0
Requires-Dist: ipykernel==6.29.5
Requires-Dist: ipython==8.18.1
Requires-Dist: isoduration==20.11.0
Requires-Dist: jedi==0.19.1
Requires-Dist: Jinja2==3.1.4
Requires-Dist: joblib==1.4.2
Requires-Dist: json5==0.9.25
Requires-Dist: jsonpointer==3.0.0
Requires-Dist: jsonschema==4.22.0
Requires-Dist: jsonschema-specifications==2023.12.1
Requires-Dist: keras==2.13.1
Requires-Dist: Keras-Preprocessing==1.1.2
Requires-Dist: kiwisolver==1.4.5
Requires-Dist: libclang==18.1.1
Requires-Dist: lxml==5.2.2
Requires-Dist: Markdown==3.6
Requires-Dist: markdown-it-py==3.0.0
Requires-Dist: MarkupSafe==2.1.5
Requires-Dist: matplotlib==3.9.0
Requires-Dist: matplotlib-inline==0.1.7
Requires-Dist: mdurl==0.1.2
Requires-Dist: mistune==3.0.2
Requires-Dist: ml-dtypes==0.3.2
Requires-Dist: multidict==6.0.5
Requires-Dist: multitasking==0.0.11
Requires-Dist: namex==0.0.8
Requires-Dist: nbclient==0.10.0
Requires-Dist: nbconvert==7.16.4
Requires-Dist: nbformat==5.10.4
Requires-Dist: nest-asyncio==1.6.0
Requires-Dist: nltk==3.8.1
Requires-Dist: notebook==7.2.1
Requires-Dist: notebook-shim==0.2.4
Requires-Dist: numpy==1.24.3
Requires-Dist: oauthlib==3.2.2
Requires-Dist: opt-einsum==3.3.0
Requires-Dist: optree==0.11.0
Requires-Dist: overrides==7.7.0
Requires-Dist: packaging==24.0
Requires-Dist: pandas==2.2.2
Requires-Dist: pandas-datareader==0.10.0
Requires-Dist: pandocfilters==1.5.1
Requires-Dist: parso==0.8.4
Requires-Dist: pathlib==1.0.1
Requires-Dist: patsy==0.5.6
Requires-Dist: peewee==3.17.5
Requires-Dist: pillow==10.3.0
Requires-Dist: platformdirs==4.2.2
Requires-Dist: plotly==5.22.0
Requires-Dist: pluggy==1.4.0
Requires-Dist: prometheus-client==0.20.0
Requires-Dist: prompt-toolkit==3.0.47
Requires-Dist: proto-plus==1.23.0
Requires-Dist: protobuf==4.25.3
Requires-Dist: psutil==6.0.0
Requires-Dist: pure-eval==0.2.3
Requires-Dist: py4j==0.10.9.7
Requires-Dist: pyarrow==16.1.0
Requires-Dist: pyasn1==0.6.0
Requires-Dist: pyasn1-modules==0.4.0
Requires-Dist: pycparser==2.22
Requires-Dist: pydeck==0.9.1
Requires-Dist: Pygments==2.18.0
Requires-Dist: pyparsing==3.1.2
Requires-Dist: pyspark==3.5.1
Requires-Dist: pytest==8.1.1
Requires-Dist: python-dateutil==2.9.0.post0
Requires-Dist: python-dotenv==1.0.1
Requires-Dist: python-json-logger==2.0.7
Requires-Dist: pytrends==4.9.2
Requires-Dist: pytz==2024.1
Requires-Dist: pywinpty==2.0.13
Requires-Dist: PyYAML==6.0.1
Requires-Dist: pyzmq==26.0.3
Requires-Dist: referencing==0.35.1
Requires-Dist: regex==2024.5.15
Requires-Dist: requests==2.31.0
Requires-Dist: requests-oauthlib==2.0.0
Requires-Dist: rfc3339-validator==0.1.4
Requires-Dist: rfc3986-validator==0.1.1
Requires-Dist: rich==13.7.1
Requires-Dist: rpds-py==0.18.1
Requires-Dist: rsa==4.9
Requires-Dist: scikit-learn==1.5.0
Requires-Dist: scipy==1.13.1
Requires-Dist: seaborn==0.13.2
Requires-Dist: Send2Trash==1.8.3
Requires-Dist: sgmllib3k==1.0.0
Requires-Dist: six==1.16.0
Requires-Dist: smmap==5.0.1
Requires-Dist: sniffio==1.3.1
Requires-Dist: soupsieve==2.5
Requires-Dist: stack-data==0.6.3
Requires-Dist: statsmodels==0.14.2
Requires-Dist: stocknews==0.9.11
Requires-Dist: streamlit==1.37.0
Requires-Dist: streamlit-tags==1.2.8
Requires-Dist: tenacity==8.3.0
Requires-Dist: tensorboard==2.13.0
Requires-Dist: tensorboard-data-server==0.7.2
Requires-Dist: tensorflow==2.13.1
Requires-Dist: termcolor==2.4.0
Requires-Dist: terminado==0.18.1
Requires-Dist: textblob==0.18.0.post0
Requires-Dist: threadpoolctl==3.5.0
Requires-Dist: tinycss2==1.3.0
Requires-Dist: toml==0.10.2
Requires-Dist: tomli==2.0.1
Requires-Dist: toolz==0.12.1
Requires-Dist: tornado==6.4
Requires-Dist: tqdm==4.66.4
Requires-Dist: traitlets==5.14.3
Requires-Dist: types-python-dateutil==2.9.0.20240316
Requires-Dist: typing-extensions==4.5.0
Requires-Dist: tzdata==2024.1
Requires-Dist: uri-template==1.3.0
Requires-Dist: uritemplate==4.1.1
Requires-Dist: urllib3==2.2.1
Requires-Dist: watchdog==4.0.1
Requires-Dist: wcwidth==0.2.13
Requires-Dist: webcolors==24.6.0
Requires-Dist: webencodings==0.5.1
Requires-Dist: websocket-client==1.8.0
Requires-Dist: Werkzeug==3.0.3
Requires-Dist: wordcloud==1.9.3
Requires-Dist: wrapt==1.16.0
Requires-Dist: yarl==1.9.4
Requires-Dist: yfinance==0.2.40
Requires-Dist: zipp==3.19.0
Requires-Dist: zope.interface==6.4.post2
